
{"sheets":{"Sheet1":[{"Conference":"Albany","Seed":"1","Team":"Connecticut"},{"Conference":"Albany","Seed":"16","Team":"St Francis"},{"Conference":"Albany","Seed":"8","Team":"Michigan"},{"Conference":"Albany","Seed":"9","Team":"Oklahoma St"},{"Conference":"Albany","Seed":"5","Team":"Duke"},{"Conference":"Albany","Seed":"12","Team":"Belmont"},{"Conference":"Albany","Seed":"4","Team":"Texas A&M"},{"Conference":"Albany","Seed":"13","Team":"Mercer"},{"Conference":"Albany","Seed":"6","Team":"DePaul"},{"Conference":"Albany","Seed":"11","Team":"Quinnipiac"},{"Conference":"Albany","Seed":"3","Team":"Florida St"},{"Conference":"Albany","Seed":"14","Team":"UAB"},{"Conference":"Albany","Seed":"7","Team":"Arizona St"},{"Conference":"Albany","Seed":"10","Team":"Rutgers"},{"Conference":"Albany","Seed":"2","Team":"South Carolina"},{"Conference":"Albany","Seed":"15","Team":"Lamar"},{"Conference":"Lexington","Seed":"1","Team":"Louisville"},{"Conference":"Lexington","Seed":"16","Team":"North Carolina A&T"},{"Conference":"Lexington","Seed":"8","Team":"Villanova"},{"Conference":"Lexington","Seed":"9","Team":"Minnesota"},{"Conference":"Lexington","Seed":"5","Team":"Missouri"},{"Conference":"Lexington","Seed":"12","Team":"Gonzaga"},{"Conference":"Lexington","Seed":"4","Team":"Stanford"},{"Conference":"Lexington","Seed":"13","Team":"UC Davis"},{"Conference":"Lexington","Seed":"6","Team":"Oregon St"},{"Conference":"Lexington","Seed":"11","Team":"N. Colorado"},{"Conference":"Lexington","Seed":"3","Team":"Ohio St"},{"Conference":"Lexington","Seed":"14","Team":"George Washington"},{"Conference":"Lexington","Seed":"7","Team":"Green Bay"},{"Conference":"Lexington","Seed":"10","Team":"Syracuse"},{"Conference":"Lexington","Seed":"2","Team":"Baylor"},{"Conference":"Lexington","Seed":"15","Team":"Liberty"},{"Conference":"Kansas City","Seed":"1","Team":"Mississippi St"},{"Conference":"Kansas City","Seed":"16","Team":"Texas Southern"},{"Conference":"Kansas City","Seed":"8","Team":"California"},{"Conference":"Kansas City","Seed":"9","Team":"Dayton"},{"Conference":"Kansas City","Seed":"5","Team":"South Florida"},{"Conference":"Kansas City","Seed":"12","Team":"Florida Gulf Coast"},{"Conference":"Kansas City","Seed":"4","Team":"NC St"},{"Conference":"Kansas City","Seed":"13","Team":"Drexel"},{"Conference":"Kansas City","Seed":"6","Team":"LSU"},{"Conference":"Kansas City","Seed":"11","Team":"Nebraska"},{"Conference":"Kansas City","Seed":"3","Team":"UCLA"},{"Conference":"Kansas City","Seed":"14","Team":"Drake"},{"Conference":"Kansas City","Seed":"7","Team":"Miami"},{"Conference":"Kansas City","Seed":"10","Team":"Buffalo"},{"Conference":"Kansas City","Seed":"2","Team":"Texas"},{"Conference":"Kansas City","Seed":"15","Team":"UALR"},{"Conference":"Spokane","Seed":"1","Team":"Notre Dame"},{"Conference":"Spokane","Seed":"16","Team":"CSU Bakersfield"},{"Conference":"Spokane","Seed":"8","Team":"Marquette"},{"Conference":"Spokane","Seed":"9","Team":"Central Michigan"},{"Conference":"Spokane","Seed":"5","Team":"Maryland"},{"Conference":"Spokane","Seed":"12","Team":"Princeton"},{"Conference":"Spokane","Seed":"4","Team":"Georgia"},{"Conference":"Spokane","Seed":"13","Team":"American"},{"Conference":"Spokane","Seed":"6","Team":"Iowa"},{"Conference":"Spokane","Seed":"11","Team":"South Dakota St"},{"Conference":"Spokane","Seed":"3","Team":"Tennessee"},{"Conference":"Spokane","Seed":"14","Team":"Maine"},{"Conference":"Spokane","Seed":"7","Team":"Virginia"},{"Conference":"Spokane","Seed":"10","Team":"Creighton"},{"Conference":"Spokane","Seed":"2","Team":"Oregon"},{"Conference":"Spokane","Seed":"15","Team":"Boise State"}]}}